{
  "nav.home": "Home",
  "nav.menu": "Menu",
  "nav.about": "About",
  "nav.contact": "Contact",
  "hero.title": "African Cuisine at Home!",
  "hero.subtitle": "Discover the best traditional African recipes",
  "cta.discover": "Explore the Menu",
  "menu.title": "Our Menu",
  "services.title": "Our Services",
  "service.ourDishes": "Our Dishes",
  "service.delivery": "Delivery",
  "service.catering": "Catering",
  "service.workshops": "Cooking Workshops",
  "service.culture": "Culture & Traditions",
  "service.recipes": "Recipes",
  "explore": "Explore",
  "discover": "Discover",
  "music.toggle": "Toggle Background Music",
  "quantity": "Quantity:",
  "rating": "Rating:",
  "favorite": "❤️ Like",
  "similar": "Similar Dishes"
}