{
  "nav.home": "Accueil",
  "nav.menu": "Menu",
  "nav.about": "À propos",
  "nav.contact": "Contact",
  "hero.title": "La Cuisine Africaine à la Maison!",
  "hero.subtitle": "Découvrez les meilleures recettes traditionnelles africaines",
  "cta.discover": "Découvrir le Menu",
  "menu.title": "Notre Menu",
  "services.title": "Nos Services",
  "service.ourDishes": "Nos Plats",
  "service.delivery": "Livraison",
  "service.catering": "Catering",
  "service.workshops": "Ateliers Culinaires",
  "service.culture": "Culture & Traditions",
  "service.recipes": "Recettes",
  "explore": "Explorer",
  "discover": "Découvrir",
  "music.toggle": "Activer/Désactiver la musique",
  "quantity": "Quantité:",
  "rating": "Note:",
  "favorite": "❤️ Aimer",
  "similar": "Plats similaires"
}